[
    {
        "binaries": {
            "spliced": [],
            "original": []
        },
        "predictions": {
            "spack-test": [
                {
                    "message": "==> Spack test 6jzulwkyberkuw7mfubkdgwvkkg2s2gz\n==> Testing package tau-2.31-7ml72fm\n============================= 1 passed of 1 specs ==============================\n",
                    "return_code": 0,
                    "prediction": true,
                    "command": "/p/vast1/build/spack/bin/spack test run /7ml72f"
                }
            ]
        },
        "libs": {
            "spliced": [
                {
                    "dep": "libdwarf@20180129%gcc@10.2.1 arch=linux-rhel7-broadwell ^bzip2@1.0.8%gcc@10.2.1~debug~pic+shared arch=linux-rhel7-broadwell ^diffutils@3.8%gcc@10.2.1 arch=linux-rhel7-broadwell ^elfutils@0.186%gcc@10.2.1~bzip2~debuginfod+nls~xz arch=linux-rhel7-broadwell ^gettext@0.21%gcc@10.2.1+bzip2+curses+git~libunistring+libxml2+tar+xz arch=linux-rhel7-broadwell ^libiconv@1.16%gcc@10.2.1 libs=shared,static arch=linux-rhel7-broadwell ^libsigsegv@2.13%gcc@10.2.1 arch=linux-rhel7-broadwell ^libxml2@2.9.12%gcc@10.2.1~python arch=linux-rhel7-broadwell ^m4@1.4.19%gcc@10.2.1+sigsegv patches=9dc5fbd,bfdffa7 arch=linux-rhel7-broadwell ^ncurses@6.2%gcc@10.2.1~symlinks+termlib abi=none arch=linux-rhel7-broadwell ^pkgconf@1.8.0%gcc@10.2.1 arch=linux-rhel7-broadwell ^tar@1.34%gcc@10.2.1 arch=linux-rhel7-broadwell ^xz@5.2.5%gcc@10.2.1~pic libs=shared,static arch=linux-rhel7-broadwell ^zlib@1.2.11%gcc@10.2.1+optimize+pic+shared arch=linux-rhel7-broadwell",
                    "paths": [
                        "/p/vast1/build/spack/opt/spack/linux-rhel7-broadwell/gcc-10.2.1/libdwarf-20180129-zryjg4aeigtmd5qpogna7c3awx32udrv/lib/libdwarf.so.1"
                    ]
                }
            ],
            "original": [
                {
                    "dep": "libdwarf@20180129%gcc@10.2.1 arch=linux-rhel7-broadwell ^bzip2@1.0.8%gcc@10.2.1~debug~pic+shared arch=linux-rhel7-broadwell ^diffutils@3.8%gcc@10.2.1 arch=linux-rhel7-broadwell ^elfutils@0.186%gcc@10.2.1~bzip2~debuginfod+nls~xz arch=linux-rhel7-broadwell ^gettext@0.21%gcc@10.2.1+bzip2+curses+git~libunistring+libxml2+tar+xz arch=linux-rhel7-broadwell ^libiconv@1.16%gcc@10.2.1 libs=shared,static arch=linux-rhel7-broadwell ^libsigsegv@2.13%gcc@10.2.1 arch=linux-rhel7-broadwell ^libxml2@2.9.12%gcc@10.2.1~python arch=linux-rhel7-broadwell ^m4@1.4.19%gcc@10.2.1+sigsegv patches=9dc5fbd,bfdffa7 arch=linux-rhel7-broadwell ^ncurses@6.2%gcc@10.2.1~symlinks+termlib abi=none arch=linux-rhel7-broadwell ^pkgconf@1.8.0%gcc@10.2.1 arch=linux-rhel7-broadwell ^tar@1.34%gcc@10.2.1 arch=linux-rhel7-broadwell ^xz@5.2.5%gcc@10.2.1~pic libs=shared,static arch=linux-rhel7-broadwell ^zlib@1.2.11%gcc@10.2.1+optimize+pic+shared arch=linux-rhel7-broadwell",
                    "paths": [
                        "/p/vast1/build/spack/opt/spack/linux-rhel7-broadwell/gcc-10.2.1/libdwarf-20180129-zryjg4aeigtmd5qpogna7c3awx32udrv/lib/libdwarf.so.1"
                    ]
                }
            ]
        },
        "experiment": "experiment",
        "result": "splice-success",
        "success": true,
        "splice": "libdwarf@20180129",
        "package": "tau@2.31"
    },
    {
        "binaries": {
            "spliced": [],
            "original": []
        },
        "predictions": {
            "spack-test": [
                {
                    "message": "==> Spack test 57i6jsfdkgxo5hvby4kpylkfdoyg2az3\n==> Testing package tau-2.31-cswzegm\n============================= 1 passed of 1 specs ==============================\n",
                    "return_code": 0,
                    "prediction": true,
                    "command": "/p/vast1/build/spack/bin/spack test run /cswzeg"
                }
            ]
        },
        "libs": {
            "spliced": [
                {
                    "dep": "libdwarf@20160507%gcc@4.9.3 arch=linux-rhel7-broadwell ^bzip2@1.0.8%gcc@4.9.3~debug~pic+shared arch=linux-rhel7-broadwell ^diffutils@3.8%gcc@4.9.3 arch=linux-rhel7-broadwell ^elfutils@0.163%gcc@4.9.3~bzip2~debuginfod+nls~xz arch=linux-rhel7-broadwell ^gettext@0.21%gcc@4.9.3+bzip2+curses+git~libunistring+libxml2+tar+xz arch=linux-rhel7-broadwell ^libiconv@1.16%gcc@4.9.3 libs=shared,static arch=linux-rhel7-broadwell ^libsigsegv@2.13%gcc@4.9.3 arch=linux-rhel7-broadwell ^libxml2@2.9.12%gcc@4.9.3~python arch=linux-rhel7-broadwell ^m4@1.4.19%gcc@4.9.3+sigsegv patches=9dc5fbd,bfdffa7 arch=linux-rhel7-broadwell ^ncurses@6.2%gcc@4.9.3~symlinks+termlib abi=none arch=linux-rhel7-broadwell ^pkgconf@1.8.0%gcc@4.9.3 arch=linux-rhel7-broadwell ^tar@1.34%gcc@4.9.3 arch=linux-rhel7-broadwell ^xz@5.2.5%gcc@4.9.3~pic libs=shared,static arch=linux-rhel7-broadwell ^zlib@1.2.11%gcc@4.9.3+optimize+pic+shared arch=linux-rhel7-broadwell",
                    "paths": [
                        "/p/vast1/build/spack/opt/spack/linux-rhel7-broadwell/gcc-4.9.3/libdwarf-20160507-733ur5fb3ajzzmuh4ghwkdmbnw2qfyzz/lib/libdwarf.so.1"
                    ]
                }
            ],
            "original": [
                {
                    "dep": "libdwarf@20180129%gcc@10.2.1 arch=linux-rhel7-broadwell ^bzip2@1.0.8%gcc@10.2.1~debug~pic+shared arch=linux-rhel7-broadwell ^diffutils@3.8%gcc@10.2.1 arch=linux-rhel7-broadwell ^elfutils@0.186%gcc@10.2.1~bzip2~debuginfod+nls~xz arch=linux-rhel7-broadwell ^gettext@0.21%gcc@10.2.1+bzip2+curses+git~libunistring+libxml2+tar+xz arch=linux-rhel7-broadwell ^libiconv@1.16%gcc@10.2.1 libs=shared,static arch=linux-rhel7-broadwell ^libsigsegv@2.13%gcc@10.2.1 arch=linux-rhel7-broadwell ^libxml2@2.9.12%gcc@10.2.1~python arch=linux-rhel7-broadwell ^m4@1.4.19%gcc@10.2.1+sigsegv patches=9dc5fbd,bfdffa7 arch=linux-rhel7-broadwell ^ncurses@6.2%gcc@10.2.1~symlinks+termlib abi=none arch=linux-rhel7-broadwell ^pkgconf@1.8.0%gcc@10.2.1 arch=linux-rhel7-broadwell ^tar@1.34%gcc@10.2.1 arch=linux-rhel7-broadwell ^xz@5.2.5%gcc@10.2.1~pic libs=shared,static arch=linux-rhel7-broadwell ^zlib@1.2.11%gcc@10.2.1+optimize+pic+shared arch=linux-rhel7-broadwell",
                    "paths": [
                        "/p/vast1/build/spack/opt/spack/linux-rhel7-broadwell/gcc-10.2.1/libdwarf-20180129-zryjg4aeigtmd5qpogna7c3awx32udrv/lib/libdwarf.so.1"
                    ]
                }
            ]
        },
        "experiment": "experiment",
        "result": "splice-success",
        "success": true,
        "splice": "libdwarf@20160507",
        "package": "tau@2.31"
    },
    {
        "binaries": {},
        "predictions": {},
        "libs": {},
        "experiment": "experiment",
        "result": "splice-install-failed",
        "success": false,
        "splice": "libdwarf@20130729",
        "package": "tau@2.31"
    },
    {
        "binaries": {},
        "predictions": {},
        "libs": {},
        "experiment": "experiment",
        "result": "splice-install-failed",
        "success": false,
        "splice": "libdwarf@20130207",
        "package": "tau@2.31"
    },
    {
        "binaries": {},
        "predictions": {},
        "libs": {},
        "experiment": "experiment",
        "result": "splice-install-failed",
        "success": false,
        "splice": "libdwarf@20130126",
        "package": "tau@2.31"
    }
]